{"basics":{"name":"Thomas Flöss","label":"Theoretical Cosmologist","image":"/assets/img/IMG_1418.PNG","email":"tsfloss@gmail.com","url":"https://thomasfloss.com/","profiles":[{"network":"Twitter","username":"tsfloss","url":"https://twitter.com/tsfloss"}]},"work":[{"name":"University of Groningen, the Netherlands","position":"PhD Candidate","startDate":"2020-09-01","endDate":"2024-08-31","summary":"supervisors:"}],"volunteer":[],"education":[{"institution":"Utrecht University, the Netherlands","area":"Theoretical Physics","studyType":"MSc.","startDate":"2016-09-01","endDate":"2018-07-01","score":"GPA 4.0"},{"institution":"Utrecht University, the Netherlands","area":"Physics & Astronomy","studyType":"BSc.","startDate":"2013-09-01","endDate":"2016-07-01","score":"GPA 4.0"}],"awards":[],"certificates":[],"publications":[],"skills":[],"languages":[{"language":"Dutch","fluency":"Native speaker"},{"language":"English","fluency":"Fluent"},{"language":"German","fluency":"Proficient"}],"interests":[],"references":[],"projects":[]}